_jsonyx.cpython-313-darwin.so
jsonyx/__init__.py
jsonyx/__main__.py
jsonyx/_decoder.py
jsonyx/_differ.py
jsonyx/_encoder.py
jsonyx/_manipulator.py
jsonyx/allow.py
jsonyx/py.typed
jsonyx/test/__init__.py
jsonyx/test/conftest.py
jsonyx/test/test_apply_filter.py
jsonyx/test/test_apply_patch.py
jsonyx/test/test_dump.py
jsonyx/test/test_dumps.py
jsonyx/test/test_jsonyx.py
jsonyx/test/test_load_query_value.py
jsonyx/test/test_loads.py
jsonyx/test/test_make_patch.py
jsonyx/test/test_paste_values.py
jsonyx/test/test_select_nodes.py
jsonyx/test/test_syntax_error.py
jsonyx/test/test_write.py
jsonyx-2.3.0.dist-info/licenses/LICENSE
jsonyx-2.3.0.dist-info/METADATA
jsonyx-2.3.0.dist-info/WHEEL
jsonyx-2.3.0.dist-info/entry_points.txt
jsonyx-2.3.0.dist-info/top_level.txt
jsonyx-2.3.0.dist-info/RECORD
